RelativeAddonsSystem/__init__.py
RelativeAddonsSystem/libraries.py
RelativeAddonsSystem/system.py
RelativeAddonsSystem/addon/__init__.py
RelativeAddonsSystem/addon/metadata.py
RelativeAddonsSystem/utils/__init__.py
RelativeAddonsSystem/utils/cache.py
RelativeAddonsSystem/utils/recursive_reload_module.py
RelativeAddonsSystem/utils/storage.py
RelativeAddonsSystem/utils/version_checker.py
RelativeAddonsSystem/utils/version_transform.py
relative_addons_system-2.6.0.dist-info/LICENSE
relative_addons_system-2.6.0.dist-info/METADATA
relative_addons_system-2.6.0.dist-info/WHEEL
relative_addons_system-2.6.0.dist-info/top_level.txt
relative_addons_system-2.6.0.dist-info/RECORD
