Metadata-Version: 2.1
Name: relative-addons-system
Version: 2.6.0
Summary: Easier way to manage your project addons
Home-page: 
Author: YoungTitanium
Author-email: "kuyugama(youngtitanium)" <mail.kuyugama@gmail.com>
License: Copyright 2022 kuyugama(youngtitanium)
Project-URL: Homepage, https://github.com/youngtitanium/RelativeAddonsSystem
Keywords: addons,system,relative,requirement,dependency,addon
Classifier: License :: OSI Approved :: MIT License
Classifier: Programming Language :: Python
Classifier: Programming Language :: Python :: 3
Classifier: Topic :: Utilities
Requires-Python: >=3.10
License-File: LICENSE
Provides-Extra: dev
Requires-Dist: black ; extra == 'dev'
